flask_api_framework/__init__.py
flask_api_framework/errors.py
flask_api_framework/ext.py
flask_api_framework/helpers.py
flask_api_framework/views.py
Flask_API_Framework-0.0.3.dist-info/LICENSE
Flask_API_Framework-0.0.3.dist-info/METADATA
Flask_API_Framework-0.0.3.dist-info/WHEEL
Flask_API_Framework-0.0.3.dist-info/top_level.txt
Flask_API_Framework-0.0.3.dist-info/RECORD
